validate_email/__init__.py
validate_email/constants.py
validate_email/dns_check.py
validate_email/domainlist_check.py
validate_email/email_address.py
validate_email/exceptions.py
validate_email/regex_check.py
validate_email/smtp_check.py
validate_email/updater.py
validate_email/validate_email.py
validate_email/data/blacklist.etag.txt
validate_email/data/blacklist.txt
py3_validate_email-1.0.10.dist-info/AUTHORS
py3_validate_email-1.0.10.dist-info/LICENSE
py3_validate_email-1.0.10.dist-info/METADATA
py3_validate_email-1.0.10.dist-info/WHEEL
py3_validate_email-1.0.10.dist-info/top_level.txt
py3_validate_email-1.0.10.dist-info/RECORD
