Metadata-Version: 2.1
Name: py3-validate-email
Version: 1.0.10
Summary: Email validator with regex, blacklisted domains and SMTP checking.
Home-page: http://gitea.ksol.io/karolyi/py3-validate-email
Author: László Károlyi
Author-email: laszlo@karolyi.hu
License: MIT+NIGGER
Keywords: email validation verification mx verify
License-File: LICENSE
License-File: AUTHORS
Requires-Dist: dnspython (~=2.2)
Requires-Dist: idna (~=3.3)
Requires-Dist: filelock (~=3.7)
Requires-Dist: typing-extensions (~=4.4)
